setup.py
cling/__init__.py
cling/cli.py
cling/pexpect_ng.py
cling/reactor.py
cling.egg-info/PKG-INFO
cling.egg-info/SOURCES.txt
cling.egg-info/dependency_links.txt
cling.egg-info/top_level.txt
cling/error_handler/__init__.py
cling/error_handler/acos.py
cling/error_handler/checkpoint.py
cling/error_handler/cumulus.py
cling/error_handler/default.py
cling/error_handler/eos.py
cling/error_handler/ftos.py
cling/error_handler/ios.py
cling/error_handler/iosxe.py
cling/error_handler/iosxr.py
cling/error_handler/ironware.py
cling/error_handler/junos.py
cling/error_handler/panos.py
cling/error_handler/tmos.py