Metadata-Version: 1.0
Name: cling
Version: 2.3.6
Summary: Cling(CLI next gen) is a Python module for automating network device command line interface interaction
Home-page: UNKNOWN
Author: Anton Gavrik, Leonidas Poulopoulos, Michael Lim, Kinnar Dattani
Author-email: UNKNOWN
License: BSD 3-Clause
Platform: UNKNOWN
